{
  "type": "FeatureCollection",
  "features": [
    {
      "type": "Feature",
      "geometry": {
        "type": "Point",
        "coordinates": [
          114.17260191015298,
          22.296994492671917
        ]
      },
      "properties": {
        "id": 1,
        "text": "术店租生实过利站",
        "azimuth_deg": 14.07,
        "face": "right",
        "distance_meters": 8.496003936965405,
        "original_lat": 22.29697593859949,
        "original_lon": 114.1725218966279,
        "image_path": "ForLease_ETST/Output_ETST/ForLease_ETST_Output_ETST_1_right_clip.jpg"
      }
    },
    {
      "type": "Feature",
      "geometry": {
        "type": "Point",
        "coordinates": [
          114.1749917449458,
          22.29803337406541
        ]
      },
      "properties": {
        "id": 32,
        "text": "童租特莎金新",
        "azimuth_deg": 223.36,
        "face": "right",
        "distance_meters": 4.389585077817862,
        "original_lat": 22.29806044738337,
        "original_lon": 114.1750227313248,
        "image_path": "ForLease_ETST/Output_ETST/ForLease_ETST_Output_ETST_32_right_clip.jpg"
      }
    },
    {
      "type": "Feature",
      "geometry": {
        "type": "Point",
        "coordinates": [
          114.17489655717613,
          22.298023491182217
        ]
      },
      "properties": {
        "id": 42,
        "text": "租特莎金新",
        "azimuth_deg": 221.69,
        "face": "right",
        "distance_meters": 5.354079068326754,
        "original_lat": 22.29805548002661,
        "original_lon": 114.1749353760623,
        "image_path": "ForLease_ETST/Output_ETST/ForLease_ETST_Output_ETST_42_right_clip.jpg"
      }
    },
    {
      "type": "Feature",
      "geometry": {
        "type": "Point",
        "coordinates": [
          114.17268048479647,
          22.298151522533566
        ]
      },
      "properties": {
        "id": 49,
        "text": "鲜租杆酒",
        "azimuth_deg": 243.12,
        "face": "back",
        "distance_meters": 7.061950655904109,
        "original_lat": 22.29820810666091,
        "original_lon": 114.172711484868,
        "image_path": "ForLease_ETST/Output_ETST/ForLease_ETST_Output_ETST_49_back_clip.jpg"
      }
    },
    {
      "type": "Feature",
      "geometry": {
        "type": "Point",
        "coordinates": [
          114.17447500877003,
          22.29788857138898
        ]
      },
      "properties": {
        "id": 57,
        "text": "旺新出租",
        "azimuth_deg": 276.93,
        "face": "back",
        "distance_meters": 5.802703645026089,
        "original_lat": 22.29794031690503,
        "original_lon": 114.1744682110732,
        "image_path": "ForLease_ETST/Output_ETST/ForLease_ETST_Output_ETST_57_back_clip.jpg"
      }
    },
    {
      "type": "Feature",
      "geometry": {
        "type": "Point",
        "coordinates": [
          114.17448117285079,
          22.297863520720835
        ]
      },
      "properties": {
        "id": 62,
        "text": "租/售",
        "azimuth_deg": 183.3,
        "face": "left",
        "distance_meters": 4.95165212997512,
        "original_lat": 22.29786608124039,
        "original_lon": 114.174529169329,
        "image_path": "ForLease_ETST/Output_ETST/ForLease_ETST_Output_ETST_62_left_clip.jpg"
      }
    },
    {
      "type": "Feature",
      "geometry": {
        "type": "Point",
        "coordinates": [
          114.17459744594613,
          22.29791993923437
        ]
      },
      "properties": {
        "id": 62,
        "text": "记租逋",
        "azimuth_deg": 40.45,
        "face": "left",
        "distance_meters": 9.241087697750821,
        "original_lat": 22.29786608124039,
        "original_lon": 114.174529169329,
        "image_path": "ForLease_ETST/Output_ETST/ForLease_ETST_Output_ETST_62_left_clip.jpg"
      }
    },
    {
      "type": "Feature",
      "geometry": {
        "type": "Point",
        "coordinates": [
          114.17237292734073,
          22.298163379758645
        ]
      },
      "properties": {
        "id": 63,
        "text": "六租育",
        "azimuth_deg": 18.38,
        "face": "left",
        "distance_meters": 9.783961734776774,
        "original_lat": 22.29813566634448,
        "original_lon": 114.1722827794781,
        "image_path": "ForLease_ETST/Output_ETST/ForLease_ETST_Output_ETST_63_left_clip.jpg"
      }
    },
    {
      "type": "Feature",
      "geometry": {
        "type": "Point",
        "coordinates": [
          114.17400237768335,
          22.29915054609816
        ]
      },
      "properties": {
        "id": 71,
        "text": "出租",
        "azimuth_deg": 45.86,
        "face": "front",
        "distance_meters": 9.641642815772517,
        "original_lat": 22.29908838987027,
        "original_lon": 114.1739371844835,
        "image_path": "ForLease_ETST/Output_ETST/ForLease_ETST_Output_ETST_71_front_clip.jpg"
      }
    },
    {
      "type": "Feature",
      "geometry": {
        "type": "Point",
        "coordinates": [
          114.17370250094555,
          22.299072457976006
        ]
      },
      "properties": {
        "id": 73,
        "text": "团即奇旧美中租心",
        "azimuth_deg": 66.4,
        "face": "right",
        "distance_meters": 9.681686725007996,
        "original_lat": 22.29899276037563,
        "original_lon": 114.1736648675596,
        "image_path": "ForLease_ETST/Output_ETST/ForLease_ETST_Output_ETST_73_right_clip.jpg"
      }
    },
    {
      "type": "Feature",
      "geometry": {
        "type": "Point",
        "coordinates": [
          114.17425067181894,
          22.29853918060968
        ]
      },
      "properties": {
        "id": 77,
        "text": "招租",
        "azimuth_deg": 94.57,
        "face": "back",
        "distance_meters": 5.527430222068683,
        "original_lat": 22.29848968494807,
        "original_lon": 114.1742549478236,
        "image_path": "ForLease_ETST/Output_ETST/ForLease_ETST_Output_ETST_77_back_clip.jpg"
      }
    },
    {
      "type": "Feature",
      "geometry": {
        "type": "Point",
        "coordinates": [
          114.17220426824711,
          22.29902164025823
        ]
      },
      "properties": {
        "id": 84,
        "text": "2楼全盾招租",
        "azimuth_deg": 24.22,
        "face": "right",
        "distance_meters": 8.569686529167576,
        "original_lat": 22.29899005886953,
        "original_lon": 114.1721283873801,
        "image_path": "ForLease_ETST/Output_ETST/ForLease_ETST_Output_ETST_84_right_clip.jpg"
      }
    },
    {
      "type": "Feature",
      "geometry": {
        "type": "Point",
        "coordinates": [
          114.17295876800539,
          22.29830830490673
        ]
      },
      "properties": {
        "id": 85,
        "text": "旺铺出租",
        "azimuth_deg": 38.8,
        "face": "front",
        "distance_meters": 8.080399680205634,
        "original_lat": 22.29826282153234,
        "original_lon": 114.17289762597,
        "image_path": "ForLease_ETST/Output_ETST/ForLease_ETST_Output_ETST_85_front_clip.jpg"
      }
    },
    {
      "type": "Feature",
      "geometry": {
        "type": "Point",
        "coordinates": [
          114.17297388205569,
          22.29831182114965
        ]
      },
      "properties": {
        "id": 85,
        "text": "尚有大量出售出租葡除歡理查陶鸟",
        "azimuth_deg": 34.78,
        "face": "front",
        "distance_meters": 9.562377615718766,
        "original_lat": 22.29826282153234,
        "original_lon": 114.17289762597,
        "image_path": "ForLease_ETST/Output_ETST/ForLease_ETST_Output_ETST_85_front_clip.jpg"
      }
    },
    {
      "type": "Feature",
      "geometry": {
        "type": "Point",
        "coordinates": [
          114.17287595807294,
          22.298330414438468
        ]
      },
      "properties": {
        "id": 85,
        "text": "租置部",
        "azimuth_deg": 106.52,
        "face": "front",
        "distance_meters": 7.848420915525781,
        "original_lat": 22.29826282153234,
        "original_lon": 114.17289762597,
        "image_path": "ForLease_ETST/Output_ETST/ForLease_ETST_Output_ETST_85_front_clip.jpg"
      }
    },
    {
      "type": "Feature",
      "geometry": {
        "type": "Point",
        "coordinates": [
          114.1729622565171,
          22.298308523679246
        ]
      },
      "properties": {
        "id": 85,
        "text": "租ForLeaselSale售",
        "azimuth_deg": 37.39,
        "face": "front",
        "distance_meters": 8.378213933617523,
        "original_lat": 22.29826282153234,
        "original_lon": 114.17289762597,
        "image_path": "ForLease_ETST/Output_ETST/ForLease_ETST_Output_ETST_85_front_clip.jpg"
      }
    },
    {
      "type": "Feature",
      "geometry": {
        "type": "Point",
        "coordinates": [
          114.17354215601192,
          22.298519064648314
        ]
      },
      "properties": {
        "id": 95,
        "text": "租",
        "azimuth_deg": 86.97,
        "face": "back",
        "distance_meters": 7.995971774404164,
        "original_lat": 22.29844733635722,
        "original_lon": 114.1735380523593,
        "image_path": "ForLease_ETST/Output_ETST/ForLease_ETST_Output_ETST_95_back_clip.jpg"
      }
    },
    {
      "type": "Feature",
      "geometry": {
        "type": "Point",
        "coordinates": [
          114.17353551870889,
          22.29841347324615
        ]
      },
      "properties": {
        "id": 95,
        "text": "5亚银租",
        "azimuth_deg": 266.04,
        "face": "back",
        "distance_meters": 3.778663058376979,
        "original_lat": 22.29844733635722,
        "original_lon": 114.1735380523593,
        "image_path": "ForLease_ETST/Output_ETST/ForLease_ETST_Output_ETST_95_back_clip.jpg"
      }
    },
    {
      "type": "Feature",
      "geometry": {
        "type": "Point",
        "coordinates": [
          114.17352750023038,
          22.299940485094023
        ]
      },
      "properties": {
        "id": 98,
        "text": "租客教际",
        "azimuth_deg": 91.96,
        "face": "front",
        "distance_meters": 5.825505598440145,
        "original_lat": 22.29988818454269,
        "original_lon": 114.1735294347299,
        "image_path": "ForLease_ETST/Output_ETST/ForLease_ETST_Output_ETST_98_front_clip.jpg"
      }
    },
    {
      "type": "Feature",
      "geometry": {
        "type": "Point",
        "coordinates": [
          114.17409920699222,
          22.29955753494245
        ]
      },
      "properties": {
        "id": 99,
        "text": "租",
        "azimuth_deg": 172.93,
        "face": "right",
        "distance_meters": 4.254145976931858,
        "original_lat": 22.29955283131087,
        "original_lon": 114.1741401974574,
        "image_path": "ForLease_ETST/Output_ETST/ForLease_ETST_Output_ETST_99_right_clip.jpg"
      }
    },
    {
      "type": "Feature",
      "geometry": {
        "type": "Point",
        "coordinates": [
          114.17408875270763,
          22.29955494274896
        ]
      },
      "properties": {
        "id": 99,
        "text": "高辣店租",
        "azimuth_deg": 177.46,
        "face": "right",
        "distance_meters": 5.303746102430546,
        "original_lat": 22.29955283131087,
        "original_lon": 114.1741401974574,
        "image_path": "ForLease_ETST/Output_ETST/ForLease_ETST_Output_ETST_99_right_clip.jpg"
      }
    },
    {
      "type": "Feature",
      "geometry": {
        "type": "Point",
        "coordinates": [
          114.17463267838248,
          22.30020622081828
        ]
      },
      "properties": {
        "id": 123,
        "text": "租售",
        "azimuth_deg": 131.04,
        "face": "back",
        "distance_meters": 8.863771594100722,
        "original_lat": 22.30014616411721,
        "original_lon": 114.1746891847102,
        "image_path": "ForLease_ETST/Output_ETST/ForLease_ETST_Output_ETST_123_back_clip.jpg"
      }
    },
    {
      "type": "Feature",
      "geometry": {
        "type": "Point",
        "coordinates": [
          114.17232534189344,
          22.29950468018154
        ]
      },
      "properties": {
        "id": 134,
        "text": "旺铺招租",
        "azimuth_deg": 242.39,
        "face": "back",
        "distance_meters": 8.241080847067108,
        "original_lat": 22.29957028033295,
        "original_lon": 114.1723624247343,
        "image_path": "ForLease_ETST/Output_ETST/ForLease_ETST_Output_ETST_134_back_clip.jpg"
      }
    },
    {
      "type": "Feature",
      "geometry": {
        "type": "Point",
        "coordinates": [
          114.1730944813357,
          22.299082527160348
        ]
      },
      "properties": {
        "id": 135,
        "text": "特租LHourly Parking",
        "azimuth_deg": 317.74,
        "face": "front",
        "distance_meters": 4.533379953115202,
        "original_lat": 22.29910991379202,
        "original_lon": 114.1730619054057,
        "image_path": "ForLease_ETST/Output_ETST/ForLease_ETST_Output_ETST_135_front_clip.jpg"
      }
    },
    {
      "type": "Feature",
      "geometry": {
        "type": "Point",
        "coordinates": [
          114.17313010787022,
          22.2991587197424
        ]
      },
      "properties": {
        "id": 135,
        "text": "時租",
        "azimuth_deg": 37.72,
        "face": "right",
        "distance_meters": 8.880434863750066,
        "original_lat": 22.29910991379202,
        "original_lon": 114.1730619054057,
        "image_path": "ForLease_ETST/Output_ETST/ForLease_ETST_Output_ETST_135_right_clip.jpg"
      }
    },
    {
      "type": "Feature",
      "geometry": {
        "type": "Point",
        "coordinates": [
          114.17395266734943,
          22.300038825452443
        ]
      },
      "properties": {
        "id": 137,
        "text": "广告位招租27376255",
        "azimuth_deg": 70.33,
        "face": "front",
        "distance_meters": 8.789892479378139,
        "original_lat": 22.29996447245957,
        "original_lon": 114.1739239405597,
        "image_path": "ForLease_ETST/Output_ETST/ForLease_ETST_Output_ETST_137_front_clip.jpg"
      }
    },
    {
      "type": "Feature",
      "geometry": {
        "type": "Point",
        "coordinates": [
          114.17377598087015,
          22.299998332959383
        ]
      },
      "properties": {
        "id": 138,
        "text": "壹告位招租27396255",
        "azimuth_deg": 132.7,
        "face": "front",
        "distance_meters": 8.184688351819856,
        "original_lat": 22.29994429912066,
        "original_lon": 114.1738298724046,
        "image_path": "ForLease_ETST/Output_ETST/ForLease_ETST_Output_ETST_138_front_clip.jpg"
      }
    },
    {
      "type": "Feature",
      "geometry": {
        "type": "Point",
        "coordinates": [
          114.17376662849864,
          22.29999568674574
        ]
      },
      "properties": {
        "id": 138,
        "text": "度告位招租27396255",
        "azimuth_deg": 138.71,
        "face": "front",
        "distance_meters": 8.66907991474362,
        "original_lat": 22.29994429912066,
        "original_lon": 114.1738298724046,
        "image_path": "ForLease_ETST/Output_ETST/ForLease_ETST_Output_ETST_138_front_clip.jpg"
      }
    },
    {
      "type": "Feature",
      "geometry": {
        "type": "Point",
        "coordinates": [
          114.1750302107403,
          22.300040524759442
        ]
      },
      "properties": {
        "id": 140,
        "text": "旺德出租",
        "azimuth_deg": 297.67,
        "face": "front",
        "distance_meters": 5.058947738688345,
        "original_lat": 22.30008077261039,
        "original_lon": 114.1750074010671,
        "image_path": "ForLease_ETST/Output_ETST/ForLease_ETST_Output_ETST_140_front_clip.jpg"
      }
    },
    {
      "type": "Feature",
      "geometry": {
        "type": "Point",
        "coordinates": [
          114.17502706321382,
          22.299994222716318
        ]
      },
      "properties": {
        "id": 140,
        "text": "天租",
        "azimuth_deg": 281.87,
        "face": "front",
        "distance_meters": 9.845257120890075,
        "original_lat": 22.30008077261039,
        "original_lon": 114.1750074010671,
        "image_path": "ForLease_ETST/Output_ETST/ForLease_ETST_Output_ETST_140_front_clip.jpg"
      }
    },
    {
      "type": "Feature",
      "geometry": {
        "type": "Point",
        "coordinates": [
          114.17499993004142,
          22.3001332764497
        ]
      },
      "properties": {
        "id": 140,
        "text": "三商电租售",
        "azimuth_deg": 97.5,
        "face": "left",
        "distance_meters": 5.895161314156361,
        "original_lat": 22.30008077261039,
        "original_lon": 114.1750074010671,
        "image_path": "ForLease_ETST/Output_ETST/ForLease_ETST_Output_ETST_140_left_clip.jpg"
      }
    },
    {
      "type": "Feature",
      "geometry": {
        "type": "Point",
        "coordinates": [
          114.17497712487912,
          22.300165770966153
        ]
      },
      "properties": {
        "id": 140,
        "text": "HFor Lease租",
        "azimuth_deg": 108.24,
        "face": "left",
        "distance_meters": 9.962600066631195,
        "original_lat": 22.30008077261039,
        "original_lon": 114.1750074010671,
        "image_path": "ForLease_ETST/Output_ETST/ForLease_ETST_Output_ETST_140_left_clip.jpg"
      }
    },
    {
      "type": "Feature",
      "geometry": {
        "type": "Point",
        "coordinates": [
          114.1728661430433,
          22.300607105884655
        ]
      },
      "properties": {
        "id": 144,
        "text": "@海底玛以租",
        "azimuth_deg": 139.23,
        "face": "right",
        "distance_meters": 2.628441790226099,
        "original_lat": 22.3005916869485,
        "original_lon": 114.1728854705593,
        "image_path": "ForLease_ETST/Output_ETST/ForLease_ETST_Output_ETST_144_right_clip.jpg"
      }
    },
    {
      "type": "Feature",
      "geometry": {
        "type": "Point",
        "coordinates": [
          114.1751975095857,
          22.30158913195184
        ]
      },
      "properties": {
        "id": 179,
        "text": "租",
        "azimuth_deg": 147.41,
        "face": "front",
        "distance_meters": 6.400932235543062,
        "original_lat": 22.30155816093075,
        "original_lon": 114.1752498730687,
        "image_path": "ForLease_ETST/Output_ETST/ForLease_ETST_Output_ETST_179_front_clip.jpg"
      }
    },
    {
      "type": "Feature",
      "geometry": {
        "type": "Point",
        "coordinates": [
          114.17519830061718,
          22.30159099120271
        ]
      },
      "properties": {
        "id": 179,
        "text": "租",
        "azimuth_deg": 145.47,
        "face": "front",
        "distance_meters": 6.447464703107269,
        "original_lat": 22.30155816093075,
        "original_lon": 114.1752498730687,
        "image_path": "ForLease_ETST/Output_ETST/ForLease_ETST_Output_ETST_179_front_clip.jpg"
      }
    },
    {
      "type": "Feature",
      "geometry": {
        "type": "Point",
        "coordinates": [
          114.17508209959894,
          22.300319929566502
        ]
      },
      "properties": {
        "id": 186,
        "text": "旺铺招租",
        "azimuth_deg": 115.04,
        "face": "front",
        "distance_meters": 9.19434115497947,
        "original_lat": 22.30024509855476,
        "original_lon": 114.1751198834189,
        "image_path": "ForLease_ETST/Output_ETST/ForLease_ETST_Output_ETST_186_front_clip.jpg"
      }
    },
    {
      "type": "Feature",
      "geometry": {
        "type": "Point",
        "coordinates": [
          114.17567202583419,
          22.300223681323466
        ]
      },
      "properties": {
        "id": 188,
        "text": "租售",
        "azimuth_deg": 53.1,
        "face": "front",
        "distance_meters": 0.6347976784538254,
        "original_lat": 22.3002191211549,
        "original_lon": 114.1756683251848,
        "image_path": "ForLease_ETST/Output_ETST/ForLease_ETST_Output_ETST_188_front_clip.jpg"
      }
    },
    {
      "type": "Feature",
      "geometry": {
        "type": "Point",
        "coordinates": [
          114.17410915657776,
          22.302735820977297
        ]
      },
      "properties": {
        "id": 210,
        "text": "租/售",
        "azimuth_deg": 308.71,
        "face": "right",
        "distance_meters": 7.556322949830489,
        "original_lat": 22.30278878863379,
        "original_lon": 114.174063273875,
        "image_path": "ForLease_ETST/Output_ETST/ForLease_ETST_Output_ETST_210_right_clip.jpg"
      }
    },
    {
      "type": "Feature",
      "geometry": {
        "type": "Point",
        "coordinates": [
          114.17228560273445,
          22.302617241208065
        ]
      },
      "properties": {
        "id": 211,
        "text": "租務查韵",
        "azimuth_deg": 231.89,
        "face": "right",
        "distance_meters": 9.338170217583713,
        "original_lat": 22.30268324486794,
        "original_lon": 114.1723415609442,
        "image_path": "ForLease_ETST/Output_ETST/ForLease_ETST_Output_ETST_211_right_clip.jpg"
      }
    }
  ]
}